cfgenvy/__init__.py
cfgenvy/env.py
cfgenvy/parser.py
cfgenvy/yaml.py
cfgenvy-2.2.2.dist-info/METADATA
cfgenvy-2.2.2.dist-info/WHEEL
cfgenvy-2.2.2.dist-info/top_level.txt
cfgenvy-2.2.2.dist-info/RECORD
