Metadata-Version: 2.1
Name: cfgenvy
Version: 2.2.2
Summary: Configuration from Environment embedded in yaml.
Author-email: Jason Lubken <jlubken@users.noreply.github.com>, Graydon Neill <grayeye@users.noreply.github.com>, Penn Signals <pennsignals@pennmedicine.upenn.edu>
License: MIT License
Project-URL: Homepage, https://github.com/pennsignals/cfgenvy
Project-URL: Source, https://github.com/pennsignals/cfgenvy
Project-URL: Tracker, https://github.com/pennsignals/cfgenvy/issues
Classifier: Development Status :: 5 - Production/Stable
Classifier: Intended Audience :: Developers
Classifier: License :: OSI Approved :: MIT License
Classifier: Operating System :: Unix
Classifier: Operating System :: POSIX
Classifier: Programming Language :: Python :: 3.9
Classifier: Programming Language :: Python :: 3.10
Classifier: Programming Language :: Python :: 3.11
Classifier: Programming Language :: Python :: 3.12
Classifier: Programming Language :: Python :: Implementation :: CPython
Classifier: Topic :: Utilities
Requires-Python: >=3.9
Requires-Dist: pyyaml>=6.0
Provides-Extra: dev
Requires-Dist: astroid; extra == "dev"
Requires-Dist: black; extra == "dev"
Requires-Dist: coverage[toml]; extra == "dev"
Requires-Dist: flake8; extra == "dev"
Requires-Dist: flake8-bugbear; extra == "dev"
Requires-Dist: flake8-commas; extra == "dev"
Requires-Dist: flake8-comprehensions; extra == "dev"
Requires-Dist: flake8-docstrings; extra == "dev"
Requires-Dist: flake8-mutable; extra == "dev"
Requires-Dist: flake8-sorted-keys; extra == "dev"
Requires-Dist: isort; extra == "dev"
Requires-Dist: mypy; extra == "dev"
Requires-Dist: pep8-naming; extra == "dev"
Requires-Dist: pre-commit; extra == "dev"
Requires-Dist: pylint; extra == "dev"
Requires-Dist: pytest; extra == "dev"
Requires-Dist: pytest-cov; extra == "dev"
Requires-Dist: types-pyyaml; extra == "dev"
